LICENSE.txt
README.md
pyproject.toml
setup.cfg
setup.py
CpuSchedulingSimulation.egg-info/PKG-INFO
CpuSchedulingSimulation.egg-info/SOURCES.txt
CpuSchedulingSimulation.egg-info/dependency_links.txt
CpuSchedulingSimulation.egg-info/requires.txt
CpuSchedulingSimulation.egg-info/top_level.txt
CpuSchedulingSimulation.egg-info/zip-safe
Cpu_scheduling_algorithms/FCFS.py
Cpu_scheduling_algorithms/RoundRobin.py
Cpu_scheduling_algorithms/SJF.py
Cpu_scheduling_algorithms/__init__.py