Metadata-Version: 2.1
Name: CpuSchedulingSimulation
Version: 1.0
Summary: See live simulation of FCFS, SJF, Round Robin algorithms in CPU scheduling
Home-page: https://github.com/harisankar01/CPU-Scheduling-Simulation
Author: Hari Hara Sankar
Author-email: hariharasankar.k.a@gmail.com
License: MIT
Keywords: CPU Scheduling algorithms Simulation
Platform: UNKNOWN
Classifier: Programming Language :: Python :: 3
Classifier: License :: OSI Approved :: MIT License
Classifier: Operating System :: OS Independent
License-File: LICENSE.txt
